frasco_users_avatar.py
setup.py
frasco_users_avatar.egg-info/PKG-INFO
frasco_users_avatar.egg-info/SOURCES.txt
frasco_users_avatar.egg-info/dependency_links.txt
frasco_users_avatar.egg-info/not-zip-safe
frasco_users_avatar.egg-info/requires.txt
frasco_users_avatar.egg-info/top_level.txt