Metadata-Version: 1.0
Name: frasco-users-avatar
Version: 0.4.2
Summary: Avatars for Frasco-Users
Home-page: http://github.com/frascoweb/frasco-users-avatar
Author: Maxime Bouroumeau-Fuseau
Author-email: maxime.bouroumeau@gmail.com
License: MIT
Platform: any
